mdinfo_exiftool/__init__.py
mdinfo_exiftool/_version.py
mdinfo_exiftool/datetime_formatter.py
mdinfo_exiftool/exiftool.py
mdinfo_exiftool/help.py
mdinfo_exiftool/mdinfo_exiftool.py
mdinfo_exiftool-0.1.1.dist-info/LICENSE
mdinfo_exiftool-0.1.1.dist-info/METADATA
mdinfo_exiftool-0.1.1.dist-info/WHEEL
mdinfo_exiftool-0.1.1.dist-info/entry_points.txt
mdinfo_exiftool-0.1.1.dist-info/top_level.txt
mdinfo_exiftool-0.1.1.dist-info/RECORD
